<?xml version="1.0" encoding="UTF-8"?>
<metadata xml:lang="en"><Esri><CreaDate>20190929</CreaDate><CreaTime>15123900</CreaTime><ArcGISFormat>1.0</ArcGISFormat><SyncOnce>FALSE</SyncOnce><DataProperties><itemProps><itemName Sync="TRUE">parcel_sales</itemName><imsContentType Sync="TRUE">002</imsContentType><itemSize Sync="TRUE">0.005</itemSize><itemLocation><linkage Sync="TRUE">file://\\POUCH2017\D$\UMD\GEOG797\Project\Capstone\parcel_sales.dbf</linkage><protocol Sync="TRUE">Local Area Network</protocol></itemLocation></itemProps><lineage><Process ToolSource="c:\program files (x86)\arcgis\desktop10.6\ArcToolbox\Toolboxes\Conversion Tools.tbx\TableToTable" Date="20190929" Time="151315">TableToTable D:\UMD\GEOG670\Final\data\generate\parcels_sales_statistics_E_2010_2014.shp D:\UMD\GEOG797\Project\Capstone parcel_sales.dbf # "id "id" true true false 10 Long 0 10 ,First,#,D:\UMD\GEOG670\Final\data\generate\parcels_sales_statistics_E_2010_2014.shp,id,-1,-1;jurscode "jurscode" true true false 4 Text 0 0 ,First,#,D:\UMD\GEOG670\Final\data\generate\parcels_sales_statistics_E_2010_2014.shp,jurscode,-1,-1;acctid "acctid" true true false 16 Text 0 0 ,First,#,D:\UMD\GEOG670\Final\data\generate\parcels_sales_statistics_E_2010_2014.shp,acctid,-1,-1;digxcord "digxcord" true true false 24 Double 15 23 ,First,#,D:\UMD\GEOG670\Final\data\generate\parcels_sales_statistics_E_2010_2014.shp,digxcord,-1,-1;digycord "digycord" true true false 24 Double 15 23 ,First,#,D:\UMD\GEOG670\Final\data\generate\parcels_sales_statistics_E_2010_2014.shp,digycord,-1,-1;ct2010 "ct2010" true true false 12 Text 0 0 ,First,#,D:\UMD\GEOG670\Final\data\generate\parcels_sales_statistics_E_2010_2014.shp,ct2010,-1,-1;bg2010 "bg2010" true true false 13 Text 0 0 ,First,#,D:\UMD\GEOG670\Final\data\generate\parcels_sales_statistics_E_2010_2014.shp,bg2010,-1,-1;geogcode "geogcode" true true false 2 Text 0 0 ,First,#,D:\UMD\GEOG670\Final\data\generate\parcels_sales_statistics_E_2010_2014.shp,geogcode,-1,-1;ooi "ooi" true true false 1 Text 0 0 ,First,#,D:\UMD\GEOG670\Final\data\generate\parcels_sales_statistics_E_2010_2014.shp,ooi,-1,-1;resityp "resityp" true true false 3 Text 0 0 ,First,#,D:\UMD\GEOG670\Final\data\generate\parcels_sales_statistics_E_2010_2014.shp,resityp,-1,-1;address "address" true true false 60 Text 0 0 ,First,#,D:\UMD\GEOG670\Final\data\generate\parcels_sales_statistics_E_2010_2014.shp,address,-1,-1;strtnum "strtnum" true true false 5 Text 0 0 ,First,#,D:\UMD\GEOG670\Final\data\generate\parcels_sales_statistics_E_2010_2014.shp,strtnum,-1,-1;strtdir "strtdir" true true false 2 Text 0 0 ,First,#,D:\UMD\GEOG670\Final\data\generate\parcels_sales_statistics_E_2010_2014.shp,strtdir,-1,-1;strtnam "strtnam" true true false 40 Text 0 0 ,First,#,D:\UMD\GEOG670\Final\data\generate\parcels_sales_statistics_E_2010_2014.shp,strtnam,-1,-1;strttyp "strttyp" true true false 5 Text 0 0 ,First,#,D:\UMD\GEOG670\Final\data\generate\parcels_sales_statistics_E_2010_2014.shp,strttyp,-1,-1;strtsfx "strtsfx" true true false 2 Text 0 0 ,First,#,D:\UMD\GEOG670\Final\data\generate\parcels_sales_statistics_E_2010_2014.shp,strtsfx,-1,-1;strtunt "strtunt" true true false 30 Text 0 0 ,First,#,D:\UMD\GEOG670\Final\data\generate\parcels_sales_statistics_E_2010_2014.shp,strtunt,-1,-1;addrtyp "addrtyp" true true false 1 Text 0 0 ,First,#,D:\UMD\GEOG670\Final\data\generate\parcels_sales_statistics_E_2010_2014.shp,addrtyp,-1,-1;city "city" true true false 30 Text 0 0 ,First,#,D:\UMD\GEOG670\Final\data\generate\parcels_sales_statistics_E_2010_2014.shp,city,-1,-1;zipcode "zipcode" true true false 5 Text 0 0 ,First,#,D:\UMD\GEOG670\Final\data\generate\parcels_sales_statistics_E_2010_2014.shp,zipcode,-1,-1;ownname1 "ownname1" true true false 34 Text 0 0 ,First,#,D:\UMD\GEOG670\Final\data\generate\parcels_sales_statistics_E_2010_2014.shp,ownname1,-1,-1;ownname2 "ownname2" true true false 34 Text 0 0 ,First,#,D:\UMD\GEOG670\Final\data\generate\parcels_sales_statistics_E_2010_2014.shp,ownname2,-1,-1;namekey "namekey" true true false 25 Text 0 0 ,First,#,D:\UMD\GEOG670\Final\data\generate\parcels_sales_statistics_E_2010_2014.shp,namekey,-1,-1;ownadd1 "ownadd1" true true false 30 Text 0 0 ,First,#,D:\UMD\GEOG670\Final\data\generate\parcels_sales_statistics_E_2010_2014.shp,ownadd1,-1,-1;ownadd2 "ownadd2" true true false 30 Text 0 0 ,First,#,D:\UMD\GEOG670\Final\data\generate\parcels_sales_statistics_E_2010_2014.shp,ownadd2,-1,-1;owncity "owncity" true true false 22 Text 0 0 ,First,#,D:\UMD\GEOG670\Final\data\generate\parcels_sales_statistics_E_2010_2014.shp,owncity,-1,-1;ownstate "ownstate" true true false 2 Text 0 0 ,First,#,D:\UMD\GEOG670\Final\data\generate\parcels_sales_statistics_E_2010_2014.shp,ownstate,-1,-1;ownerzip "ownerzip" true true false 5 Text 0 0 ,First,#,D:\UMD\GEOG670\Final\data\generate\parcels_sales_statistics_E_2010_2014.shp,ownerzip,-1,-1;ownzip2 "ownzip2" true true false 4 Text 0 0 ,First,#,D:\UMD\GEOG670\Final\data\generate\parcels_sales_statistics_E_2010_2014.shp,ownzip2,-1,-1;premsnum "premsnum" true true false 5 Text 0 0 ,First,#,D:\UMD\GEOG670\Final\data\generate\parcels_sales_statistics_E_2010_2014.shp,premsnum,-1,-1;premsdir "premsdir" true true false 2 Text 0 0 ,First,#,D:\UMD\GEOG670\Final\data\generate\parcels_sales_statistics_E_2010_2014.shp,premsdir,-1,-1;premsnam "premsnam" true true false 22 Text 0 0 ,First,#,D:\UMD\GEOG670\Final\data\generate\parcels_sales_statistics_E_2010_2014.shp,premsnam,-1,-1;premstyp "premstyp" true true false 5 Text 0 0 ,First,#,D:\UMD\GEOG670\Final\data\generate\parcels_sales_statistics_E_2010_2014.shp,premstyp,-1,-1;premcity "premcity" true true false 22 Text 0 0 ,First,#,D:\UMD\GEOG670\Final\data\generate\parcels_sales_statistics_E_2010_2014.shp,premcity,-1,-1;premzip "premzip" true true false 5 Text 0 0 ,First,#,D:\UMD\GEOG670\Final\data\generate\parcels_sales_statistics_E_2010_2014.shp,premzip,-1,-1;premzip2 "premzip2" true true false 4 Text 0 0 ,First,#,D:\UMD\GEOG670\Final\data\generate\parcels_sales_statistics_E_2010_2014.shp,premzip2,-1,-1;legal1 "legal1" true true false 24 Text 0 0 ,First,#,D:\UMD\GEOG670\Final\data\generate\parcels_sales_statistics_E_2010_2014.shp,legal1,-1,-1;legal2 "legal2" true true false 24 Text 0 0 ,First,#,D:\UMD\GEOG670\Final\data\generate\parcels_sales_statistics_E_2010_2014.shp,legal2,-1,-1;legal3 "legal3" true true false 24 Text 0 0 ,First,#,D:\UMD\GEOG670\Final\data\generate\parcels_sales_statistics_E_2010_2014.shp,legal3,-1,-1;dr1clerk "dr1clerk" true true false 3 Text 0 0 ,First,#,D:\UMD\GEOG670\Final\data\generate\parcels_sales_statistics_E_2010_2014.shp,dr1clerk,-1,-1;dr1liber "dr1liber" true true false 5 Text 0 0 ,First,#,D:\UMD\GEOG670\Final\data\generate\parcels_sales_statistics_E_2010_2014.shp,dr1liber,-1,-1;dr1folio "dr1folio" true true false 4 Text 0 0 ,First,#,D:\UMD\GEOG670\Final\data\generate\parcels_sales_statistics_E_2010_2014.shp,dr1folio,-1,-1;towncode "towncode" true true false 3 Text 0 0 ,First,#,D:\UMD\GEOG670\Final\data\generate\parcels_sales_statistics_E_2010_2014.shp,towncode,-1,-1;desctown "desctown" true true false 25 Text 0 0 ,First,#,D:\UMD\GEOG670\Final\data\generate\parcels_sales_statistics_E_2010_2014.shp,desctown,-1,-1;subdivsn "subdivsn" true true false 4 Text 0 0 ,First,#,D:\UMD\GEOG670\Final\data\generate\parcels_sales_statistics_E_2010_2014.shp,subdivsn,-1,-1;dsubcode "dsubcode" true true false 6 Text 0 0 ,First,#,D:\UMD\GEOG670\Final\data\generate\parcels_sales_statistics_E_2010_2014.shp,dsubcode,-1,-1;descsubd "descsubd" true true false 75 Text 0 0 ,First,#,D:\UMD\GEOG670\Final\data\generate\parcels_sales_statistics_E_2010_2014.shp,descsubd,-1,-1;plat "plat" true true false 6 Text 0 0 ,First,#,D:\UMD\GEOG670\Final\data\generate\parcels_sales_statistics_E_2010_2014.shp,plat,-1,-1;pltliber "pltliber" true true false 7 Text 0 0 ,First,#,D:\UMD\GEOG670\Final\data\generate\parcels_sales_statistics_E_2010_2014.shp,pltliber,-1,-1;pltfolio "pltfolio" true true false 4 Text 0 0 ,First,#,D:\UMD\GEOG670\Final\data\generate\parcels_sales_statistics_E_2010_2014.shp,pltfolio,-1,-1;section "section" true true false 3 Text 0 0 ,First,#,D:\UMD\GEOG670\Final\data\generate\parcels_sales_statistics_E_2010_2014.shp,section,-1,-1;block "block" true true false 5 Text 0 0 ,First,#,D:\UMD\GEOG670\Final\data\generate\parcels_sales_statistics_E_2010_2014.shp,block,-1,-1;lot "lot" true true false 5 Text 0 0 ,First,#,D:\UMD\GEOG670\Final\data\generate\parcels_sales_statistics_E_2010_2014.shp,lot,-1,-1;map "map" true true false 5 Text 0 0 ,First,#,D:\UMD\GEOG670\Final\data\generate\parcels_sales_statistics_E_2010_2014.shp,map,-1,-1;grid "grid" true true false 5 Text 0 0 ,First,#,D:\UMD\GEOG670\Final\data\generate\parcels_sales_statistics_E_2010_2014.shp,grid,-1,-1;parcel "parcel" true true false 5 Text 0 0 ,First,#,D:\UMD\GEOG670\Final\data\generate\parcels_sales_statistics_E_2010_2014.shp,parcel,-1,-1;zoning "zoning" true true false 5 Text 0 0 ,First,#,D:\UMD\GEOG670\Final\data\generate\parcels_sales_statistics_E_2010_2014.shp,zoning,-1,-1;znchgdat "znchgdat" true true false 8 Text 0 0 ,First,#,D:\UMD\GEOG670\Final\data\generate\parcels_sales_statistics_E_2010_2014.shp,znchgdat,-1,-1;rzrealdat "rzrealdat" true true false 8 Text 0 0 ,First,#,D:\UMD\GEOG670\Final\data\generate\parcels_sales_statistics_E_2010_2014.shp,rzrealdat,-1,-1;ciuse "ciuse" true true false 5 Text 0 0 ,First,#,D:\UMD\GEOG670\Final\data\generate\parcels_sales_statistics_E_2010_2014.shp,ciuse,-1,-1;descciuse "descciuse" true true false 60 Text 0 0 ,First,#,D:\UMD\GEOG670\Final\data\generate\parcels_sales_statistics_E_2010_2014.shp,descciuse,-1,-1;exclass "exclass" true true false 3 Text 0 0 ,First,#,D:\UMD\GEOG670\Final\data\generate\parcels_sales_statistics_E_2010_2014.shp,exclass,-1,-1;descexcl "descexcl" true true false 60 Text 0 0 ,First,#,D:\UMD\GEOG670\Final\data\generate\parcels_sales_statistics_E_2010_2014.shp,descexcl,-1,-1;lu "lu" true true false 2 Text 0 0 ,First,#,D:\UMD\GEOG670\Final\data\generate\parcels_sales_statistics_E_2010_2014.shp,lu,-1,-1;desclu "desclu" true true false 23 Text 0 0 ,First,#,D:\UMD\GEOG670\Final\data\generate\parcels_sales_statistics_E_2010_2014.shp,desclu,-1,-1;acres "acres" true true false 24 Double 15 23 ,First,#,D:\UMD\GEOG670\Final\data\generate\parcels_sales_statistics_E_2010_2014.shp,acres,-1,-1;landarea "landarea" true true false 24 Double 15 23 ,First,#,D:\UMD\GEOG670\Final\data\generate\parcels_sales_statistics_E_2010_2014.shp,landarea,-1,-1;luom "luom" true true false 1 Text 0 0 ,First,#,D:\UMD\GEOG670\Final\data\generate\parcels_sales_statistics_E_2010_2014.shp,luom,-1,-1;width "width" true true false 24 Double 15 23 ,First,#,D:\UMD\GEOG670\Final\data\generate\parcels_sales_statistics_E_2010_2014.shp,width,-1,-1;depth "depth" true true false 24 Double 15 23 ,First,#,D:\UMD\GEOG670\Final\data\generate\parcels_sales_statistics_E_2010_2014.shp,depth,-1,-1;pfuw "pfuw" true true false 1 Text 0 0 ,First,#,D:\UMD\GEOG670\Final\data\generate\parcels_sales_statistics_E_2010_2014.shp,pfuw,-1,-1;pfus "pfus" true true false 1 Text 0 0 ,First,#,D:\UMD\GEOG670\Final\data\generate\parcels_sales_statistics_E_2010_2014.shp,pfus,-1,-1;pflw "pflw" true true false 1 Text 0 0 ,First,#,D:\UMD\GEOG670\Final\data\generate\parcels_sales_statistics_E_2010_2014.shp,pflw,-1,-1;pfsp "pfsp" true true false 1 Text 0 0 ,First,#,D:\UMD\GEOG670\Final\data\generate\parcels_sales_statistics_E_2010_2014.shp,pfsp,-1,-1;pfsu "pfsu" true true false 1 Text 0 0 ,First,#,D:\UMD\GEOG670\Final\data\generate\parcels_sales_statistics_E_2010_2014.shp,pfsu,-1,-1;pfic "pfic" true true false 1 Text 0 0 ,First,#,D:\UMD\GEOG670\Final\data\generate\parcels_sales_statistics_E_2010_2014.shp,pfic,-1,-1;pfih "pfih" true true false 1 Text 0 0 ,First,#,D:\UMD\GEOG670\Final\data\generate\parcels_sales_statistics_E_2010_2014.shp,pfih,-1,-1;recind "recind" true true false 1 Text 0 0 ,First,#,D:\UMD\GEOG670\Final\data\generate\parcels_sales_statistics_E_2010_2014.shp,recind,-1,-1;permittyp "permittyp" true true false 3 Text 0 0 ,First,#,D:\UMD\GEOG670\Final\data\generate\parcels_sales_statistics_E_2010_2014.shp,permittyp,-1,-1;yearblt "yearblt" true true false 4 Text 0 0 ,First,#,D:\UMD\GEOG670\Final\data\generate\parcels_sales_statistics_E_2010_2014.shp,yearblt,-1,-1;sqftstrc "sqftstrc" true true false 10 Long 0 10 ,First,#,D:\UMD\GEOG670\Final\data\generate\parcels_sales_statistics_E_2010_2014.shp,sqftstrc,-1,-1;strugrad "strugrad" true true false 1 Text 0 0 ,First,#,D:\UMD\GEOG670\Final\data\generate\parcels_sales_statistics_E_2010_2014.shp,strugrad,-1,-1;descgrad "descgrad" true true false 20 Text 0 0 ,First,#,D:\UMD\GEOG670\Final\data\generate\parcels_sales_statistics_E_2010_2014.shp,descgrad,-1,-1;strucnst "strucnst" true true false 4 Text 0 0 ,First,#,D:\UMD\GEOG670\Final\data\generate\parcels_sales_statistics_E_2010_2014.shp,strucnst,-1,-1;desccnst "desccnst" true true false 25 Text 0 0 ,First,#,D:\UMD\GEOG670\Final\data\generate\parcels_sales_statistics_E_2010_2014.shp,desccnst,-1,-1;strustyl "strustyl" true true false 4 Text 0 0 ,First,#,D:\UMD\GEOG670\Final\data\generate\parcels_sales_statistics_E_2010_2014.shp,strustyl,-1,-1;descstyl "descstyl" true true false 45 Text 0 0 ,First,#,D:\UMD\GEOG670\Final\data\generate\parcels_sales_statistics_E_2010_2014.shp,descstyl,-1,-1;strubldg "strubldg" true true false 4 Text 0 0 ,First,#,D:\UMD\GEOG670\Final\data\generate\parcels_sales_statistics_E_2010_2014.shp,strubldg,-1,-1;descbldg "descbldg" true true false 45 Text 0 0 ,First,#,D:\UMD\GEOG670\Final\data\generate\parcels_sales_statistics_E_2010_2014.shp,descbldg,-1,-1;lastinsp "lastinsp" true true false 6 Text 0 0 ,First,#,D:\UMD\GEOG670\Final\data\generate\parcels_sales_statistics_E_2010_2014.shp,lastinsp,-1,-1;lastassd "lastassd" true true false 6 Text 0 0 ,First,#,D:\UMD\GEOG670\Final\data\generate\parcels_sales_statistics_E_2010_2014.shp,lastassd,-1,-1;assessor "assessor" true true false 4 Text 0 0 ,First,#,D:\UMD\GEOG670\Final\data\generate\parcels_sales_statistics_E_2010_2014.shp,assessor,-1,-1;transno1 "transno1" true true false 6 Text 0 0 ,First,#,D:\UMD\GEOG670\Final\data\generate\parcels_sales_statistics_E_2010_2014.shp,transno1,-1,-1;grntnam1 "grntnam1" true true false 34 Text 0 0 ,First,#,D:\UMD\GEOG670\Final\data\generate\parcels_sales_statistics_E_2010_2014.shp,grntnam1,-1,-1;gr1clrk1 "gr1clrk1" true true false 3 Text 0 0 ,First,#,D:\UMD\GEOG670\Final\data\generate\parcels_sales_statistics_E_2010_2014.shp,gr1clrk1,-1,-1;gr1libr1 "gr1libr1" true true false 5 Text 0 0 ,First,#,D:\UMD\GEOG670\Final\data\generate\parcels_sales_statistics_E_2010_2014.shp,gr1libr1,-1,-1;gr1folo1 "gr1folo1" true true false 4 Text 0 0 ,First,#,D:\UMD\GEOG670\Final\data\generate\parcels_sales_statistics_E_2010_2014.shp,gr1folo1,-1,-1;convey1 "convey1" true true false 1 Text 0 0 ,First,#,D:\UMD\GEOG670\Final\data\generate\parcels_sales_statistics_E_2010_2014.shp,convey1,-1,-1;tradate "tradate" true true false 8 Text 0 0 ,First,#,D:\UMD\GEOG670\Final\data\generate\parcels_sales_statistics_E_2010_2014.shp,tradate,-1,-1;considr1 "considr1" true true false 10 Long 0 10 ,First,#,D:\UMD\GEOG670\Final\data\generate\parcels_sales_statistics_E_2010_2014.shp,considr1,-1,-1;mortgag1 "mortgag1" true true false 10 Long 0 10 ,First,#,D:\UMD\GEOG670\Final\data\generate\parcels_sales_statistics_E_2010_2014.shp,mortgag1,-1,-1;nfmlndvl "nfmlndvl" true true false 10 Long 0 10 ,First,#,D:\UMD\GEOG670\Final\data\generate\parcels_sales_statistics_E_2010_2014.shp,nfmlndvl,-1,-1;nfmimpvl "nfmimpvl" true true false 10 Long 0 10 ,First,#,D:\UMD\GEOG670\Final\data\generate\parcels_sales_statistics_E_2010_2014.shp,nfmimpvl,-1,-1;nfmttlvl "nfmttlvl" true true false 20 Double 0 20 ,First,#,D:\UMD\GEOG670\Final\data\generate\parcels_sales_statistics_E_2010_2014.shp,nfmttlvl,-1,-1;crtarcod "crtarcod" true true false 2 Text 0 0 ,First,#,D:\UMD\GEOG670\Final\data\generate\parcels_sales_statistics_E_2010_2014.shp,crtarcod,-1,-1;fcmacode "fcmacode" true true false 1 Text 0 0 ,First,#,D:\UMD\GEOG670\Final\data\generate\parcels_sales_statistics_E_2010_2014.shp,fcmacode,-1,-1;agfndarea "agfndarea" true true false 24 Double 15 23 ,First,#,D:\UMD\GEOG670\Final\data\generate\parcels_sales_statistics_E_2010_2014.shp,agfndarea,-1,-1;agfndluom "agfndluom" true true false 1 Text 0 0 ,First,#,D:\UMD\GEOG670\Final\data\generate\parcels_sales_statistics_E_2010_2014.shp,agfndluom,-1,-1;entzndat "entzndat" true true false 8 Text 0 0 ,First,#,D:\UMD\GEOG670\Final\data\generate\parcels_sales_statistics_E_2010_2014.shp,entzndat,-1,-1;entznassm "entznassm" true true false 10 Long 0 10 ,First,#,D:\UMD\GEOG670\Final\data\generate\parcels_sales_statistics_E_2010_2014.shp,entznassm,-1,-1;plndevdat "plndevdat" true true false 8 Text 0 0 ,First,#,D:\UMD\GEOG670\Final\data\generate\parcels_sales_statistics_E_2010_2014.shp,plndevdat,-1,-1;nprctstdat "nprctstdat" true true false 8 Text 0 0 ,First,#,D:\UMD\GEOG670\Final\data\generate\parcels_sales_statistics_E_2010_2014.shp,nprctstdat,-1,-1;nprcarea "nprcarea" true true false 24 Double 15 23 ,First,#,D:\UMD\GEOG670\Final\data\generate\parcels_sales_statistics_E_2010_2014.shp,nprcarea,-1,-1;nprcluom "nprcluom" true true false 1 Text 0 0 ,First,#,D:\UMD\GEOG670\Final\data\generate\parcels_sales_statistics_E_2010_2014.shp,nprcluom,-1,-1;homqlcod "homqlcod" true true false 1 Text 0 0 ,First,#,D:\UMD\GEOG670\Final\data\generate\parcels_sales_statistics_E_2010_2014.shp,homqlcod,-1,-1;homqldat "homqldat" true true false 8 Text 0 0 ,First,#,D:\UMD\GEOG670\Final\data\generate\parcels_sales_statistics_E_2010_2014.shp,homqldat,-1,-1;bldg_story "bldg_story" true true false 10 Text 0 0 ,First,#,D:\UMD\GEOG670\Final\data\generate\parcels_sales_statistics_E_2010_2014.shp,bldg_story,-1,-1;bldg_units "bldg_units" true true false 20 Double 0 20 ,First,#,D:\UMD\GEOG670\Final\data\generate\parcels_sales_statistics_E_2010_2014.shp,bldg_units,-1,-1;resident "resident" true true false 10 Long 0 10 ,First,#,D:\UMD\GEOG670\Final\data\generate\parcels_sales_statistics_E_2010_2014.shp,resident,-1,-1;resi2010 "resi2010" true true false 10 Long 0 10 ,First,#,D:\UMD\GEOG670\Final\data\generate\parcels_sales_statistics_E_2010_2014.shp,resi2010,-1,-1;resi2000 "resi2000" true true false 10 Long 0 10 ,First,#,D:\UMD\GEOG670\Final\data\generate\parcels_sales_statistics_E_2010_2014.shp,resi2000,-1,-1;resi1990 "resi1990" true true false 10 Long 0 10 ,First,#,D:\UMD\GEOG670\Final\data\generate\parcels_sales_statistics_E_2010_2014.shp,resi1990,-1,-1;resiuths "resiuths" true true false 10 Long 0 10 ,First,#,D:\UMD\GEOG670\Final\data\generate\parcels_sales_statistics_E_2010_2014.shp,resiuths,-1,-1;aprtment "aprtment" true true false 10 Long 0 10 ,First,#,D:\UMD\GEOG670\Final\data\generate\parcels_sales_statistics_E_2010_2014.shp,aprtment,-1,-1;trailer "trailer" true true false 10 Long 0 10 ,First,#,D:\UMD\GEOG670\Final\data\generate\parcels_sales_statistics_E_2010_2014.shp,trailer,-1,-1;special "special" true true false 10 Long 0 10 ,First,#,D:\UMD\GEOG670\Final\data\generate\parcels_sales_statistics_E_2010_2014.shp,special,-1,-1;other "other" true true false 10 Long 0 10 ,First,#,D:\UMD\GEOG670\Final\data\generate\parcels_sales_statistics_E_2010_2014.shp,other,-1,-1;ptype "ptype" true true false 10 Long 0 10 ,First,#,D:\UMD\GEOG670\Final\data\generate\parcels_sales_statistics_E_2010_2014.shp,ptype,-1,-1;sdatwebadr "sdatwebadr" true true false 140 Text 0 0 ,First,#,D:\UMD\GEOG670\Final\data\generate\parcels_sales_statistics_E_2010_2014.shp,sdatwebadr,-1,-1;existing "existing" true true false 11 Text 0 0 ,First,#,D:\UMD\GEOG670\Final\data\generate\parcels_sales_statistics_E_2010_2014.shp,existing,-1,-1;seqnumb "seqnumb" true true false 10 Long 0 10 ,First,#,D:\UMD\GEOG670\Final\data\generate\parcels_sales_statistics_E_2010_2014.shp,seqnumb,-1,-1;salesfacto "salesfacto" true true false 24 Double 15 23 ,First,#,D:\UMD\GEOG670\Final\data\generate\parcels_sales_statistics_E_2010_2014.shp,salesfacto,-1,-1;layer "layer" true true false 100 Text 0 0 ,First,#,D:\UMD\GEOG670\Final\data\generate\parcels_sales_statistics_E_2010_2014.shp,layer,-1,-1;sf_date "sf_date" true true false 8 Text 0 0 ,First,#,D:\UMD\GEOG670\Final\data\generate\parcels_sales_statistics_E_2010_2014.shp,sf_date,-1,-1;sf_propval "sf_propval" true true false 24 Double 15 23 ,First,#,D:\UMD\GEOG670\Final\data\generate\parcels_sales_statistics_E_2010_2014.shp,sf_propval,-1,-1;value_2010 "value_2010" true true false 24 Double 15 23 ,First,#,D:\UMD\GEOG670\Final\data\generate\parcels_sales_statistics_E_2010_2014.shp,value_2010,-1,-1;value_2011 "value_2011" true true false 24 Double 15 23 ,First,#,D:\UMD\GEOG670\Final\data\generate\parcels_sales_statistics_E_2010_2014.shp,value_2011,-1,-1;value_2012 "value_2012" true true false 24 Double 15 23 ,First,#,D:\UMD\GEOG670\Final\data\generate\parcels_sales_statistics_E_2010_2014.shp,value_2012,-1,-1;value_2013 "value_2013" true true false 24 Double 15 23 ,First,#,D:\UMD\GEOG670\Final\data\generate\parcels_sales_statistics_E_2010_2014.shp,value_2013,-1,-1;value_2014 "value_2014" true true false 24 Double 15 23 ,First,#,D:\UMD\GEOG670\Final\data\generate\parcels_sales_statistics_E_2010_2014.shp,value_2014,-1,-1;AvgVel "AvgVel" true true false 24 Double 15 23 ,First,#,D:\UMD\GEOG670\Final\data\generate\parcels_sales_statistics_E_2010_2014.shp,AvgVel,-1,-1;fid_1 "fid_1" true true false 10 Long 0 10 ,First,#,D:\UMD\GEOG670\Final\data\generate\parcels_sales_statistics_E_2010_2014.shp,fid_1,-1,-1;cntyname "cntyname" true true false 25 Text 0 0 ,First,#,D:\UMD\GEOG670\Final\data\generate\parcels_sales_statistics_E_2010_2014.shp,cntyname,-1,-1;county "county" true true false 5 Text 0 0 ,First,#,D:\UMD\GEOG670\Final\data\generate\parcels_sales_statistics_E_2010_2014.shp,county,-1,-1;ct2010_2 "ct2010_2" true true false 16 Text 0 0 ,First,#,D:\UMD\GEOG670\Final\data\generate\parcels_sales_statistics_E_2010_2014.shp,ct2010_2,-1,-1;hutype "hutype" true true false 10 Text 0 0 ,First,#,D:\UMD\GEOG670\Final\data\generate\parcels_sales_statistics_E_2010_2014.shp,hutype,-1,-1;sales2010 "sales2010" true true false 10 Long 0 10 ,First,#,D:\UMD\GEOG670\Final\data\generate\parcels_sales_statistics_E_2010_2014.shp,sales2010,-1,-1;med_2010 "med_2010" true true false 10 Long 0 10 ,First,#,D:\UMD\GEOG670\Final\data\generate\parcels_sales_statistics_E_2010_2014.shp,med_2010,-1,-1;mean_2010 "mean_2010" true true false 10 Long 0 10 ,First,#,D:\UMD\GEOG670\Final\data\generate\parcels_sales_statistics_E_2010_2014.shp,mean_2010,-1,-1;sales2011 "sales2011" true true false 20 Double 0 20 ,First,#,D:\UMD\GEOG670\Final\data\generate\parcels_sales_statistics_E_2010_2014.shp,sales2011,-1,-1;med_2011 "med_2011" true true false 20 Double 0 20 ,First,#,D:\UMD\GEOG670\Final\data\generate\parcels_sales_statistics_E_2010_2014.shp,med_2011,-1,-1;mean_2011 "mean_2011" true true false 20 Double 0 20 ,First,#,D:\UMD\GEOG670\Final\data\generate\parcels_sales_statistics_E_2010_2014.shp,mean_2011,-1,-1;sales2012 "sales2012" true true false 20 Double 0 20 ,First,#,D:\UMD\GEOG670\Final\data\generate\parcels_sales_statistics_E_2010_2014.shp,sales2012,-1,-1;med_2012 "med_2012" true true false 20 Double 0 20 ,First,#,D:\UMD\GEOG670\Final\data\generate\parcels_sales_statistics_E_2010_2014.shp,med_2012,-1,-1;mean_2012 "mean_2012" true true false 20 Double 0 20 ,First,#,D:\UMD\GEOG670\Final\data\generate\parcels_sales_statistics_E_2010_2014.shp,mean_2012,-1,-1;sales2013 "sales2013" true true false 20 Double 0 20 ,First,#,D:\UMD\GEOG670\Final\data\generate\parcels_sales_statistics_E_2010_2014.shp,sales2013,-1,-1;med_2013 "med_2013" true true false 20 Double 0 20 ,First,#,D:\UMD\GEOG670\Final\data\generate\parcels_sales_statistics_E_2010_2014.shp,med_2013,-1,-1;mean_2013 "mean_2013" true true false 20 Double 0 20 ,First,#,D:\UMD\GEOG670\Final\data\generate\parcels_sales_statistics_E_2010_2014.shp,mean_2013,-1,-1;sales2014 "sales2014" true true false 20 Double 0 20 ,First,#,D:\UMD\GEOG670\Final\data\generate\parcels_sales_statistics_E_2010_2014.shp,sales2014,-1,-1;med_2014 "med_2014" true true false 20 Double 0 20 ,First,#,D:\UMD\GEOG670\Final\data\generate\parcels_sales_statistics_E_2010_2014.shp,med_2014,-1,-1;mean_2014 "mean_2014" true true false 20 Double 0 20 ,First,#,D:\UMD\GEOG670\Final\data\generate\parcels_sales_statistics_E_2010_2014.shp,mean_2014,-1,-1;OBJECTID_1 "OBJECTID_1" true true false 10 Long 0 10 ,First,#,D:\UMD\GEOG670\Final\data\generate\parcels_sales_statistics_E_2010_2014.shp,OBJECTID_1,-1,-1;TAG "TAG" true true false 80 Text 0 0 ,First,#,D:\UMD\GEOG670\Final\data\generate\parcels_sales_statistics_E_2010_2014.shp,TAG,-1,-1;S_TYPE "S_TYPE" true true false 254 Text 0 0 ,First,#,D:\UMD\GEOG670\Final\data\generate\parcels_sales_statistics_E_2010_2014.shp,S_TYPE,-1,-1;TAG_NAME "TAG_NAME" true true false 254 Text 0 0 ,First,#,D:\UMD\GEOG670\Final\data\generate\parcels_sales_statistics_E_2010_2014.shp,TAG_NAME,-1,-1;FScore "FScore" true true false 19 Double 11 18 ,First,#,D:\UMD\GEOG670\Final\data\generate\parcels_sales_statistics_E_2010_2014.shp,FScore,-1,-1" #</Process></lineage></DataProperties><SyncDate>20190929</SyncDate><SyncTime>15123900</SyncTime><ModDate>20190929</ModDate><ModTime>15123900</ModTime></Esri><dataIdInfo><envirDesc Sync="TRUE"> Version 6.2 (Build 9200) ; Esri ArcGIS 10.6.1.9270</envirDesc><dataLang><languageCode value="eng" Sync="TRUE"></languageCode><countryCode value="USA" Sync="TRUE"></countryCode></dataLang><idCitation><resTitle Sync="TRUE">parcel_sales</resTitle><presForm><PresFormCd value="011" Sync="TRUE"></PresFormCd></presForm></idCitation><spatRpType><SpatRepTypCd value="003" Sync="TRUE"></SpatRepTypCd></spatRpType></dataIdInfo><mdLang><languageCode value="eng" Sync="TRUE"></languageCode><countryCode value="USA" Sync="TRUE"></countryCode></mdLang><mdChar><CharSetCd value="004" Sync="TRUE"></CharSetCd></mdChar><distInfo><distFormat><formatName Sync="TRUE">dBASE Table</formatName></distFormat><distTranOps><transSize Sync="TRUE">0.005</transSize></distTranOps></distInfo><mdHrLv><ScopeCd value="007" Sync="TRUE"></ScopeCd></mdHrLv><mdHrLvName Sync="TRUE">dataset</mdHrLvName><eainfo><detailed Name="parcel_sales"><enttyp><enttypl Sync="TRUE">parcel_sales</enttypl><enttypt Sync="TRUE">Table</enttypt><enttypc Sync="TRUE">0</enttypc></enttyp><attr><attrlabl Sync="TRUE">OID</attrlabl><attalias Sync="TRUE">OID</attalias><attrtype Sync="TRUE">OID</attrtype><attwidth Sync="TRUE">4</attwidth><atprecis Sync="TRUE">0</atprecis><attscale Sync="TRUE">0</attscale><attrdef Sync="TRUE">Internal feature number.</attrdef><attrdefs Sync="TRUE">Esri</attrdefs><attrdomv><udom Sync="TRUE">Sequential unique whole numbers that are automatically generated.</udom></attrdomv></attr><attr><attrlabl Sync="TRUE">id</attrlabl><attalias Sync="TRUE">id</attalias><attrtype Sync="TRUE">Integer</attrtype><attwidth Sync="TRUE">10</attwidth><atprecis Sync="TRUE">10</atprecis><attscale Sync="TRUE">0</attscale></attr><attr><attrlabl Sync="TRUE">jurscode</attrlabl><attalias Sync="TRUE">jurscode</attalias><attrtype Sync="TRUE">String</attrtype><attwidth Sync="TRUE">4</attwidth><atprecis Sync="TRUE">0</atprecis><attscale Sync="TRUE">0</attscale></attr><attr><attrlabl Sync="TRUE">acctid</attrlabl><attalias Sync="TRUE">acctid</attalias><attrtype Sync="TRUE">String</attrtype><attwidth Sync="TRUE">16</attwidth><atprecis Sync="TRUE">0</atprecis><attscale Sync="TRUE">0</attscale></attr><attr><attrlabl Sync="TRUE">digxcord</attrlabl><attalias Sync="TRUE">digxcord</attalias><attrtype Sync="TRUE">Double</attrtype><attwidth Sync="TRUE">19</attwidth><atprecis Sync="TRUE">18</atprecis><attscale Sync="TRUE">15</attscale></attr><attr><attrlabl Sync="TRUE">digycord</attrlabl><attalias Sync="TRUE">digycord</attalias><attrtype Sync="TRUE">Double</attrtype><attwidth Sync="TRUE">19</attwidth><atprecis Sync="TRUE">18</atprecis><attscale Sync="TRUE">15</attscale></attr><attr><attrlabl Sync="TRUE">ct2010</attrlabl><attalias Sync="TRUE">ct2010</attalias><attrtype Sync="TRUE">String</attrtype><attwidth Sync="TRUE">12</attwidth><atprecis Sync="TRUE">0</atprecis><attscale Sync="TRUE">0</attscale></attr><attr><attrlabl Sync="TRUE">bg2010</attrlabl><attalias Sync="TRUE">bg2010</attalias><attrtype Sync="TRUE">String</attrtype><attwidth Sync="TRUE">13</attwidth><atprecis Sync="TRUE">0</atprecis><attscale Sync="TRUE">0</attscale></attr><attr><attrlabl Sync="TRUE">geogcode</attrlabl><attalias Sync="TRUE">geogcode</attalias><attrtype Sync="TRUE">String</attrtype><attwidth Sync="TRUE">2</attwidth><atprecis Sync="TRUE">0</atprecis><attscale Sync="TRUE">0</attscale></attr><attr><attrlabl Sync="TRUE">ooi</attrlabl><attalias Sync="TRUE">ooi</attalias><attrtype Sync="TRUE">String</attrtype><attwidth Sync="TRUE">1</attwidth><atprecis Sync="TRUE">0</atprecis><attscale Sync="TRUE">0</attscale></attr><attr><attrlabl Sync="TRUE">resityp</attrlabl><attalias Sync="TRUE">resityp</attalias><attrtype Sync="TRUE">String</attrtype><attwidth Sync="TRUE">3</attwidth><atprecis Sync="TRUE">0</atprecis><attscale Sync="TRUE">0</attscale></attr><attr><attrlabl Sync="TRUE">address</attrlabl><attalias Sync="TRUE">address</attalias><attrtype Sync="TRUE">String</attrtype><attwidth Sync="TRUE">60</attwidth><atprecis Sync="TRUE">0</atprecis><attscale Sync="TRUE">0</attscale></attr><attr><attrlabl Sync="TRUE">strtnum</attrlabl><attalias Sync="TRUE">strtnum</attalias><attrtype Sync="TRUE">String</attrtype><attwidth Sync="TRUE">5</attwidth><atprecis Sync="TRUE">0</atprecis><attscale Sync="TRUE">0</attscale></attr><attr><attrlabl Sync="TRUE">strtdir</attrlabl><attalias Sync="TRUE">strtdir</attalias><attrtype Sync="TRUE">String</attrtype><attwidth Sync="TRUE">2</attwidth><atprecis Sync="TRUE">0</atprecis><attscale Sync="TRUE">0</attscale></attr><attr><attrlabl Sync="TRUE">strtnam</attrlabl><attalias Sync="TRUE">strtnam</attalias><attrtype Sync="TRUE">String</attrtype><attwidth Sync="TRUE">40</attwidth><atprecis Sync="TRUE">0</atprecis><attscale Sync="TRUE">0</attscale></attr><attr><attrlabl Sync="TRUE">strttyp</attrlabl><attalias Sync="TRUE">strttyp</attalias><attrtype Sync="TRUE">String</attrtype><attwidth Sync="TRUE">5</attwidth><atprecis Sync="TRUE">0</atprecis><attscale Sync="TRUE">0</attscale></attr><attr><attrlabl Sync="TRUE">strtsfx</attrlabl><attalias Sync="TRUE">strtsfx</attalias><attrtype Sync="TRUE">String</attrtype><attwidth Sync="TRUE">2</attwidth><atprecis Sync="TRUE">0</atprecis><attscale Sync="TRUE">0</attscale></attr><attr><attrlabl Sync="TRUE">strtunt</attrlabl><attalias Sync="TRUE">strtunt</attalias><attrtype Sync="TRUE">String</attrtype><attwidth Sync="TRUE">30</attwidth><atprecis Sync="TRUE">0</atprecis><attscale Sync="TRUE">0</attscale></attr><attr><attrlabl Sync="TRUE">addrtyp</attrlabl><attalias Sync="TRUE">addrtyp</attalias><attrtype Sync="TRUE">String</attrtype><attwidth Sync="TRUE">1</attwidth><atprecis Sync="TRUE">0</atprecis><attscale Sync="TRUE">0</attscale></attr><attr><attrlabl Sync="TRUE">city</attrlabl><attalias Sync="TRUE">city</attalias><attrtype Sync="TRUE">String</attrtype><attwidth Sync="TRUE">30</attwidth><atprecis Sync="TRUE">0</atprecis><attscale Sync="TRUE">0</attscale></attr><attr><attrlabl Sync="TRUE">zipcode</attrlabl><attalias Sync="TRUE">zipcode</attalias><attrtype Sync="TRUE">String</attrtype><attwidth Sync="TRUE">5</attwidth><atprecis Sync="TRUE">0</atprecis><attscale Sync="TRUE">0</attscale></attr><attr><attrlabl Sync="TRUE">ownname1</attrlabl><attalias Sync="TRUE">ownname1</attalias><attrtype Sync="TRUE">String</attrtype><attwidth Sync="TRUE">34</attwidth><atprecis Sync="TRUE">0</atprecis><attscale Sync="TRUE">0</attscale></attr><attr><attrlabl Sync="TRUE">ownname2</attrlabl><attalias Sync="TRUE">ownname2</attalias><attrtype Sync="TRUE">String</attrtype><attwidth Sync="TRUE">34</attwidth><atprecis Sync="TRUE">0</atprecis><attscale Sync="TRUE">0</attscale></attr><attr><attrlabl Sync="TRUE">namekey</attrlabl><attalias Sync="TRUE">namekey</attalias><attrtype Sync="TRUE">String</attrtype><attwidth Sync="TRUE">25</attwidth><atprecis Sync="TRUE">0</atprecis><attscale Sync="TRUE">0</attscale></attr><attr><attrlabl Sync="TRUE">ownadd1</attrlabl><attalias Sync="TRUE">ownadd1</attalias><attrtype Sync="TRUE">String</attrtype><attwidth Sync="TRUE">30</attwidth><atprecis Sync="TRUE">0</atprecis><attscale Sync="TRUE">0</attscale></attr><attr><attrlabl Sync="TRUE">ownadd2</attrlabl><attalias Sync="TRUE">ownadd2</attalias><attrtype Sync="TRUE">String</attrtype><attwidth Sync="TRUE">30</attwidth><atprecis Sync="TRUE">0</atprecis><attscale Sync="TRUE">0</attscale></attr><attr><attrlabl Sync="TRUE">owncity</attrlabl><attalias Sync="TRUE">owncity</attalias><attrtype Sync="TRUE">String</attrtype><attwidth Sync="TRUE">22</attwidth><atprecis Sync="TRUE">0</atprecis><attscale Sync="TRUE">0</attscale></attr><attr><attrlabl Sync="TRUE">ownstate</attrlabl><attalias Sync="TRUE">ownstate</attalias><attrtype Sync="TRUE">String</attrtype><attwidth Sync="TRUE">2</attwidth><atprecis Sync="TRUE">0</atprecis><attscale Sync="TRUE">0</attscale></attr><attr><attrlabl Sync="TRUE">ownerzip</attrlabl><attalias Sync="TRUE">ownerzip</attalias><attrtype Sync="TRUE">String</attrtype><attwidth Sync="TRUE">5</attwidth><atprecis Sync="TRUE">0</atprecis><attscale Sync="TRUE">0</attscale></attr><attr><attrlabl Sync="TRUE">ownzip2</attrlabl><attalias Sync="TRUE">ownzip2</attalias><attrtype Sync="TRUE">String</attrtype><attwidth Sync="TRUE">4</attwidth><atprecis Sync="TRUE">0</atprecis><attscale Sync="TRUE">0</attscale></attr><attr><attrlabl Sync="TRUE">premsnum</attrlabl><attalias Sync="TRUE">premsnum</attalias><attrtype Sync="TRUE">String</attrtype><attwidth Sync="TRUE">5</attwidth><atprecis Sync="TRUE">0</atprecis><attscale Sync="TRUE">0</attscale></attr><attr><attrlabl Sync="TRUE">premsdir</attrlabl><attalias Sync="TRUE">premsdir</attalias><attrtype Sync="TRUE">String</attrtype><attwidth Sync="TRUE">2</attwidth><atprecis Sync="TRUE">0</atprecis><attscale Sync="TRUE">0</attscale></attr><attr><attrlabl Sync="TRUE">premsnam</attrlabl><attalias Sync="TRUE">premsnam</attalias><attrtype Sync="TRUE">String</attrtype><attwidth Sync="TRUE">22</attwidth><atprecis Sync="TRUE">0</atprecis><attscale Sync="TRUE">0</attscale></attr><attr><attrlabl Sync="TRUE">premstyp</attrlabl><attalias Sync="TRUE">premstyp</attalias><attrtype Sync="TRUE">String</attrtype><attwidth Sync="TRUE">5</attwidth><atprecis Sync="TRUE">0</atprecis><attscale Sync="TRUE">0</attscale></attr><attr><attrlabl Sync="TRUE">premcity</attrlabl><attalias Sync="TRUE">premcity</attalias><attrtype Sync="TRUE">String</attrtype><attwidth Sync="TRUE">22</attwidth><atprecis Sync="TRUE">0</atprecis><attscale Sync="TRUE">0</attscale></attr><attr><attrlabl Sync="TRUE">premzip</attrlabl><attalias Sync="TRUE">premzip</attalias><attrtype Sync="TRUE">String</attrtype><attwidth Sync="TRUE">5</attwidth><atprecis Sync="TRUE">0</atprecis><attscale Sync="TRUE">0</attscale></attr><attr><attrlabl Sync="TRUE">premzip2</attrlabl><attalias Sync="TRUE">premzip2</attalias><attrtype Sync="TRUE">String</attrtype><attwidth Sync="TRUE">4</attwidth><atprecis Sync="TRUE">0</atprecis><attscale Sync="TRUE">0</attscale></attr><attr><attrlabl Sync="TRUE">legal1</attrlabl><attalias Sync="TRUE">legal1</attalias><attrtype Sync="TRUE">String</attrtype><attwidth Sync="TRUE">24</attwidth><atprecis Sync="TRUE">0</atprecis><attscale Sync="TRUE">0</attscale></attr><attr><attrlabl Sync="TRUE">legal2</attrlabl><attalias Sync="TRUE">legal2</attalias><attrtype Sync="TRUE">String</attrtype><attwidth Sync="TRUE">24</attwidth><atprecis Sync="TRUE">0</atprecis><attscale Sync="TRUE">0</attscale></attr><attr><attrlabl Sync="TRUE">legal3</attrlabl><attalias Sync="TRUE">legal3</attalias><attrtype Sync="TRUE">String</attrtype><attwidth Sync="TRUE">24</attwidth><atprecis Sync="TRUE">0</atprecis><attscale Sync="TRUE">0</attscale></attr><attr><attrlabl Sync="TRUE">dr1clerk</attrlabl><attalias Sync="TRUE">dr1clerk</attalias><attrtype Sync="TRUE">String</attrtype><attwidth Sync="TRUE">3</attwidth><atprecis Sync="TRUE">0</atprecis><attscale Sync="TRUE">0</attscale></attr><attr><attrlabl Sync="TRUE">dr1liber</attrlabl><attalias Sync="TRUE">dr1liber</attalias><attrtype Sync="TRUE">String</attrtype><attwidth Sync="TRUE">5</attwidth><atprecis Sync="TRUE">0</atprecis><attscale Sync="TRUE">0</attscale></attr><attr><attrlabl Sync="TRUE">dr1folio</attrlabl><attalias Sync="TRUE">dr1folio</attalias><attrtype Sync="TRUE">String</attrtype><attwidth Sync="TRUE">4</attwidth><atprecis Sync="TRUE">0</atprecis><attscale Sync="TRUE">0</attscale></attr><attr><attrlabl Sync="TRUE">towncode</attrlabl><attalias Sync="TRUE">towncode</attalias><attrtype Sync="TRUE">String</attrtype><attwidth Sync="TRUE">3</attwidth><atprecis Sync="TRUE">0</atprecis><attscale Sync="TRUE">0</attscale></attr><attr><attrlabl Sync="TRUE">desctown</attrlabl><attalias Sync="TRUE">desctown</attalias><attrtype Sync="TRUE">String</attrtype><attwidth Sync="TRUE">25</attwidth><atprecis Sync="TRUE">0</atprecis><attscale Sync="TRUE">0</attscale></attr><attr><attrlabl Sync="TRUE">subdivsn</attrlabl><attalias Sync="TRUE">subdivsn</attalias><attrtype Sync="TRUE">String</attrtype><attwidth Sync="TRUE">4</attwidth><atprecis Sync="TRUE">0</atprecis><attscale Sync="TRUE">0</attscale></attr><attr><attrlabl Sync="TRUE">dsubcode</attrlabl><attalias Sync="TRUE">dsubcode</attalias><attrtype Sync="TRUE">String</attrtype><attwidth Sync="TRUE">6</attwidth><atprecis Sync="TRUE">0</atprecis><attscale Sync="TRUE">0</attscale></attr><attr><attrlabl Sync="TRUE">descsubd</attrlabl><attalias Sync="TRUE">descsubd</attalias><attrtype Sync="TRUE">String</attrtype><attwidth Sync="TRUE">75</attwidth><atprecis Sync="TRUE">0</atprecis><attscale Sync="TRUE">0</attscale></attr><attr><attrlabl Sync="TRUE">plat</attrlabl><attalias Sync="TRUE">plat</attalias><attrtype Sync="TRUE">String</attrtype><attwidth Sync="TRUE">6</attwidth><atprecis Sync="TRUE">0</atprecis><attscale Sync="TRUE">0</attscale></attr><attr><attrlabl Sync="TRUE">pltliber</attrlabl><attalias Sync="TRUE">pltliber</attalias><attrtype Sync="TRUE">String</attrtype><attwidth Sync="TRUE">7</attwidth><atprecis Sync="TRUE">0</atprecis><attscale Sync="TRUE">0</attscale></attr><attr><attrlabl Sync="TRUE">pltfolio</attrlabl><attalias Sync="TRUE">pltfolio</attalias><attrtype Sync="TRUE">String</attrtype><attwidth Sync="TRUE">4</attwidth><atprecis Sync="TRUE">0</atprecis><attscale Sync="TRUE">0</attscale></attr><attr><attrlabl Sync="TRUE">section</attrlabl><attalias Sync="TRUE">section</attalias><attrtype Sync="TRUE">String</attrtype><attwidth Sync="TRUE">3</attwidth><atprecis Sync="TRUE">0</atprecis><attscale Sync="TRUE">0</attscale></attr><attr><attrlabl Sync="TRUE">block</attrlabl><attalias Sync="TRUE">block</attalias><attrtype Sync="TRUE">String</attrtype><attwidth Sync="TRUE">5</attwidth><atprecis Sync="TRUE">0</atprecis><attscale Sync="TRUE">0</attscale></attr><attr><attrlabl Sync="TRUE">lot</attrlabl><attalias Sync="TRUE">lot</attalias><attrtype Sync="TRUE">String</attrtype><attwidth Sync="TRUE">5</attwidth><atprecis Sync="TRUE">0</atprecis><attscale Sync="TRUE">0</attscale></attr><attr><attrlabl Sync="TRUE">map</attrlabl><attalias Sync="TRUE">map</attalias><attrtype Sync="TRUE">String</attrtype><attwidth Sync="TRUE">5</attwidth><atprecis Sync="TRUE">0</atprecis><attscale Sync="TRUE">0</attscale></attr><attr><attrlabl Sync="TRUE">grid</attrlabl><attalias Sync="TRUE">grid</attalias><attrtype Sync="TRUE">String</attrtype><attwidth Sync="TRUE">5</attwidth><atprecis Sync="TRUE">0</atprecis><attscale Sync="TRUE">0</attscale></attr><attr><attrlabl Sync="TRUE">parcel</attrlabl><attalias Sync="TRUE">parcel</attalias><attrtype Sync="TRUE">String</attrtype><attwidth Sync="TRUE">5</attwidth><atprecis Sync="TRUE">0</atprecis><attscale Sync="TRUE">0</attscale></attr><attr><attrlabl Sync="TRUE">zoning</attrlabl><attalias Sync="TRUE">zoning</attalias><attrtype Sync="TRUE">String</attrtype><attwidth Sync="TRUE">5</attwidth><atprecis Sync="TRUE">0</atprecis><attscale Sync="TRUE">0</attscale></attr><attr><attrlabl Sync="TRUE">znchgdat</attrlabl><attalias Sync="TRUE">znchgdat</attalias><attrtype Sync="TRUE">String</attrtype><attwidth Sync="TRUE">8</attwidth><atprecis Sync="TRUE">0</atprecis><attscale Sync="TRUE">0</attscale></attr><attr><attrlabl Sync="TRUE">rzrealdat</attrlabl><attalias Sync="TRUE">rzrealdat</attalias><attrtype Sync="TRUE">String</attrtype><attwidth Sync="TRUE">8</attwidth><atprecis Sync="TRUE">0</atprecis><attscale Sync="TRUE">0</attscale></attr><attr><attrlabl Sync="TRUE">ciuse</attrlabl><attalias Sync="TRUE">ciuse</attalias><attrtype Sync="TRUE">String</attrtype><attwidth Sync="TRUE">5</attwidth><atprecis Sync="TRUE">0</atprecis><attscale Sync="TRUE">0</attscale></attr><attr><attrlabl Sync="TRUE">descciuse</attrlabl><attalias Sync="TRUE">descciuse</attalias><attrtype Sync="TRUE">String</attrtype><attwidth Sync="TRUE">60</attwidth><atprecis Sync="TRUE">0</atprecis><attscale Sync="TRUE">0</attscale></attr><attr><attrlabl Sync="TRUE">exclass</attrlabl><attalias Sync="TRUE">exclass</attalias><attrtype Sync="TRUE">String</attrtype><attwidth Sync="TRUE">3</attwidth><atprecis Sync="TRUE">0</atprecis><attscale Sync="TRUE">0</attscale></attr><attr><attrlabl Sync="TRUE">descexcl</attrlabl><attalias Sync="TRUE">descexcl</attalias><attrtype Sync="TRUE">String</attrtype><attwidth Sync="TRUE">60</attwidth><atprecis Sync="TRUE">0</atprecis><attscale Sync="TRUE">0</attscale></attr><attr><attrlabl Sync="TRUE">lu</attrlabl><attalias Sync="TRUE">lu</attalias><attrtype Sync="TRUE">String</attrtype><attwidth Sync="TRUE">2</attwidth><atprecis Sync="TRUE">0</atprecis><attscale Sync="TRUE">0</attscale></attr><attr><attrlabl Sync="TRUE">desclu</attrlabl><attalias Sync="TRUE">desclu</attalias><attrtype Sync="TRUE">String</attrtype><attwidth Sync="TRUE">23</attwidth><atprecis Sync="TRUE">0</atprecis><attscale Sync="TRUE">0</attscale></attr><attr><attrlabl Sync="TRUE">acres</attrlabl><attalias Sync="TRUE">acres</attalias><attrtype Sync="TRUE">Double</attrtype><attwidth Sync="TRUE">19</attwidth><atprecis Sync="TRUE">18</atprecis><attscale Sync="TRUE">15</attscale></attr><attr><attrlabl Sync="TRUE">landarea</attrlabl><attalias Sync="TRUE">landarea</attalias><attrtype Sync="TRUE">Double</attrtype><attwidth Sync="TRUE">19</attwidth><atprecis Sync="TRUE">18</atprecis><attscale Sync="TRUE">15</attscale></attr><attr><attrlabl Sync="TRUE">luom</attrlabl><attalias Sync="TRUE">luom</attalias><attrtype Sync="TRUE">String</attrtype><attwidth Sync="TRUE">1</attwidth><atprecis Sync="TRUE">0</atprecis><attscale Sync="TRUE">0</attscale></attr><attr><attrlabl Sync="TRUE">width</attrlabl><attalias Sync="TRUE">width</attalias><attrtype Sync="TRUE">Double</attrtype><attwidth Sync="TRUE">19</attwidth><atprecis Sync="TRUE">18</atprecis><attscale Sync="TRUE">15</attscale></attr><attr><attrlabl Sync="TRUE">depth</attrlabl><attalias Sync="TRUE">depth</attalias><attrtype Sync="TRUE">Double</attrtype><attwidth Sync="TRUE">19</attwidth><atprecis Sync="TRUE">18</atprecis><attscale Sync="TRUE">15</attscale></attr><attr><attrlabl Sync="TRUE">pfuw</attrlabl><attalias Sync="TRUE">pfuw</attalias><attrtype Sync="TRUE">String</attrtype><attwidth Sync="TRUE">1</attwidth><atprecis Sync="TRUE">0</atprecis><attscale Sync="TRUE">0</attscale></attr><attr><attrlabl Sync="TRUE">pfus</attrlabl><attalias Sync="TRUE">pfus</attalias><attrtype Sync="TRUE">String</attrtype><attwidth Sync="TRUE">1</attwidth><atprecis Sync="TRUE">0</atprecis><attscale Sync="TRUE">0</attscale></attr><attr><attrlabl Sync="TRUE">pflw</attrlabl><attalias Sync="TRUE">pflw</attalias><attrtype Sync="TRUE">String</attrtype><attwidth Sync="TRUE">1</attwidth><atprecis Sync="TRUE">0</atprecis><attscale Sync="TRUE">0</attscale></attr><attr><attrlabl Sync="TRUE">pfsp</attrlabl><attalias Sync="TRUE">pfsp</attalias><attrtype Sync="TRUE">String</attrtype><attwidth Sync="TRUE">1</attwidth><atprecis Sync="TRUE">0</atprecis><attscale Sync="TRUE">0</attscale></attr><attr><attrlabl Sync="TRUE">pfsu</attrlabl><attalias Sync="TRUE">pfsu</attalias><attrtype Sync="TRUE">String</attrtype><attwidth Sync="TRUE">1</attwidth><atprecis Sync="TRUE">0</atprecis><attscale Sync="TRUE">0</attscale></attr><attr><attrlabl Sync="TRUE">pfic</attrlabl><attalias Sync="TRUE">pfic</attalias><attrtype Sync="TRUE">String</attrtype><attwidth Sync="TRUE">1</attwidth><atprecis Sync="TRUE">0</atprecis><attscale Sync="TRUE">0</attscale></attr><attr><attrlabl Sync="TRUE">pfih</attrlabl><attalias Sync="TRUE">pfih</attalias><attrtype Sync="TRUE">String</attrtype><attwidth Sync="TRUE">1</attwidth><atprecis Sync="TRUE">0</atprecis><attscale Sync="TRUE">0</attscale></attr><attr><attrlabl Sync="TRUE">recind</attrlabl><attalias Sync="TRUE">recind</attalias><attrtype Sync="TRUE">String</attrtype><attwidth Sync="TRUE">1</attwidth><atprecis Sync="TRUE">0</atprecis><attscale Sync="TRUE">0</attscale></attr><attr><attrlabl Sync="TRUE">permittyp</attrlabl><attalias Sync="TRUE">permittyp</attalias><attrtype Sync="TRUE">String</attrtype><attwidth Sync="TRUE">3</attwidth><atprecis Sync="TRUE">0</atprecis><attscale Sync="TRUE">0</attscale></attr><attr><attrlabl Sync="TRUE">yearblt</attrlabl><attalias Sync="TRUE">yearblt</attalias><attrtype Sync="TRUE">String</attrtype><attwidth Sync="TRUE">4</attwidth><atprecis Sync="TRUE">0</atprecis><attscale Sync="TRUE">0</attscale></attr><attr><attrlabl Sync="TRUE">sqftstrc</attrlabl><attalias Sync="TRUE">sqftstrc</attalias><attrtype Sync="TRUE">Integer</attrtype><attwidth Sync="TRUE">10</attwidth><atprecis Sync="TRUE">10</atprecis><attscale Sync="TRUE">0</attscale></attr><attr><attrlabl Sync="TRUE">strugrad</attrlabl><attalias Sync="TRUE">strugrad</attalias><attrtype Sync="TRUE">String</attrtype><attwidth Sync="TRUE">1</attwidth><atprecis Sync="TRUE">0</atprecis><attscale Sync="TRUE">0</attscale></attr><attr><attrlabl Sync="TRUE">descgrad</attrlabl><attalias Sync="TRUE">descgrad</attalias><attrtype Sync="TRUE">String</attrtype><attwidth Sync="TRUE">20</attwidth><atprecis Sync="TRUE">0</atprecis><attscale Sync="TRUE">0</attscale></attr><attr><attrlabl Sync="TRUE">strucnst</attrlabl><attalias Sync="TRUE">strucnst</attalias><attrtype Sync="TRUE">String</attrtype><attwidth Sync="TRUE">4</attwidth><atprecis Sync="TRUE">0</atprecis><attscale Sync="TRUE">0</attscale></attr><attr><attrlabl Sync="TRUE">desccnst</attrlabl><attalias Sync="TRUE">desccnst</attalias><attrtype Sync="TRUE">String</attrtype><attwidth Sync="TRUE">25</attwidth><atprecis Sync="TRUE">0</atprecis><attscale Sync="TRUE">0</attscale></attr><attr><attrlabl Sync="TRUE">strustyl</attrlabl><attalias Sync="TRUE">strustyl</attalias><attrtype Sync="TRUE">String</attrtype><attwidth Sync="TRUE">4</attwidth><atprecis Sync="TRUE">0</atprecis><attscale Sync="TRUE">0</attscale></attr><attr><attrlabl Sync="TRUE">descstyl</attrlabl><attalias Sync="TRUE">descstyl</attalias><attrtype Sync="TRUE">String</attrtype><attwidth Sync="TRUE">45</attwidth><atprecis Sync="TRUE">0</atprecis><attscale Sync="TRUE">0</attscale></attr><attr><attrlabl Sync="TRUE">strubldg</attrlabl><attalias Sync="TRUE">strubldg</attalias><attrtype Sync="TRUE">String</attrtype><attwidth Sync="TRUE">4</attwidth><atprecis Sync="TRUE">0</atprecis><attscale Sync="TRUE">0</attscale></attr><attr><attrlabl Sync="TRUE">descbldg</attrlabl><attalias Sync="TRUE">descbldg</attalias><attrtype Sync="TRUE">String</attrtype><attwidth Sync="TRUE">45</attwidth><atprecis Sync="TRUE">0</atprecis><attscale Sync="TRUE">0</attscale></attr><attr><attrlabl Sync="TRUE">lastinsp</attrlabl><attalias Sync="TRUE">lastinsp</attalias><attrtype Sync="TRUE">String</attrtype><attwidth Sync="TRUE">6</attwidth><atprecis Sync="TRUE">0</atprecis><attscale Sync="TRUE">0</attscale></attr><attr><attrlabl Sync="TRUE">lastassd</attrlabl><attalias Sync="TRUE">lastassd</attalias><attrtype Sync="TRUE">String</attrtype><attwidth Sync="TRUE">6</attwidth><atprecis Sync="TRUE">0</atprecis><attscale Sync="TRUE">0</attscale></attr><attr><attrlabl Sync="TRUE">assessor</attrlabl><attalias Sync="TRUE">assessor</attalias><attrtype Sync="TRUE">String</attrtype><attwidth Sync="TRUE">4</attwidth><atprecis Sync="TRUE">0</atprecis><attscale Sync="TRUE">0</attscale></attr><attr><attrlabl Sync="TRUE">transno1</attrlabl><attalias Sync="TRUE">transno1</attalias><attrtype Sync="TRUE">String</attrtype><attwidth Sync="TRUE">6</attwidth><atprecis Sync="TRUE">0</atprecis><attscale Sync="TRUE">0</attscale></attr><attr><attrlabl Sync="TRUE">grntnam1</attrlabl><attalias Sync="TRUE">grntnam1</attalias><attrtype Sync="TRUE">String</attrtype><attwidth Sync="TRUE">34</attwidth><atprecis Sync="TRUE">0</atprecis><attscale Sync="TRUE">0</attscale></attr><attr><attrlabl Sync="TRUE">gr1clrk1</attrlabl><attalias Sync="TRUE">gr1clrk1</attalias><attrtype Sync="TRUE">String</attrtype><attwidth Sync="TRUE">3</attwidth><atprecis Sync="TRUE">0</atprecis><attscale Sync="TRUE">0</attscale></attr><attr><attrlabl Sync="TRUE">gr1libr1</attrlabl><attalias Sync="TRUE">gr1libr1</attalias><attrtype Sync="TRUE">String</attrtype><attwidth Sync="TRUE">5</attwidth><atprecis Sync="TRUE">0</atprecis><attscale Sync="TRUE">0</attscale></attr><attr><attrlabl Sync="TRUE">gr1folo1</attrlabl><attalias Sync="TRUE">gr1folo1</attalias><attrtype Sync="TRUE">String</attrtype><attwidth Sync="TRUE">4</attwidth><atprecis Sync="TRUE">0</atprecis><attscale Sync="TRUE">0</attscale></attr><attr><attrlabl Sync="TRUE">convey1</attrlabl><attalias Sync="TRUE">convey1</attalias><attrtype Sync="TRUE">String</attrtype><attwidth Sync="TRUE">1</attwidth><atprecis Sync="TRUE">0</atprecis><attscale Sync="TRUE">0</attscale></attr><attr><attrlabl Sync="TRUE">tradate</attrlabl><attalias Sync="TRUE">tradate</attalias><attrtype Sync="TRUE">String</attrtype><attwidth Sync="TRUE">8</attwidth><atprecis Sync="TRUE">0</atprecis><attscale Sync="TRUE">0</attscale></attr><attr><attrlabl Sync="TRUE">considr1</attrlabl><attalias Sync="TRUE">considr1</attalias><attrtype Sync="TRUE">Integer</attrtype><attwidth Sync="TRUE">10</attwidth><atprecis Sync="TRUE">10</atprecis><attscale Sync="TRUE">0</attscale></attr><attr><attrlabl Sync="TRUE">mortgag1</attrlabl><attalias Sync="TRUE">mortgag1</attalias><attrtype Sync="TRUE">Integer</attrtype><attwidth Sync="TRUE">10</attwidth><atprecis Sync="TRUE">10</atprecis><attscale Sync="TRUE">0</attscale></attr><attr><attrlabl Sync="TRUE">nfmlndvl</attrlabl><attalias Sync="TRUE">nfmlndvl</attalias><attrtype Sync="TRUE">Integer</attrtype><attwidth Sync="TRUE">10</attwidth><atprecis Sync="TRUE">10</atprecis><attscale Sync="TRUE">0</attscale></attr><attr><attrlabl Sync="TRUE">nfmimpvl</attrlabl><attalias Sync="TRUE">nfmimpvl</attalias><attrtype Sync="TRUE">Integer</attrtype><attwidth Sync="TRUE">10</attwidth><atprecis Sync="TRUE">10</atprecis><attscale Sync="TRUE">0</attscale></attr><attr><attrlabl Sync="TRUE">nfmttlvl</attrlabl><attalias Sync="TRUE">nfmttlvl</attalias><attrtype Sync="TRUE">Double</attrtype><attwidth Sync="TRUE">19</attwidth><atprecis Sync="TRUE">19</atprecis><attscale Sync="TRUE">0</attscale></attr><attr><attrlabl Sync="TRUE">crtarcod</attrlabl><attalias Sync="TRUE">crtarcod</attalias><attrtype Sync="TRUE">String</attrtype><attwidth Sync="TRUE">2</attwidth><atprecis Sync="TRUE">0</atprecis><attscale Sync="TRUE">0</attscale></attr><attr><attrlabl Sync="TRUE">fcmacode</attrlabl><attalias Sync="TRUE">fcmacode</attalias><attrtype Sync="TRUE">String</attrtype><attwidth Sync="TRUE">1</attwidth><atprecis Sync="TRUE">0</atprecis><attscale Sync="TRUE">0</attscale></attr><attr><attrlabl Sync="TRUE">agfndarea</attrlabl><attalias Sync="TRUE">agfndarea</attalias><attrtype Sync="TRUE">Double</attrtype><attwidth Sync="TRUE">19</attwidth><atprecis Sync="TRUE">18</atprecis><attscale Sync="TRUE">15</attscale></attr><attr><attrlabl Sync="TRUE">agfndluom</attrlabl><attalias Sync="TRUE">agfndluom</attalias><attrtype Sync="TRUE">String</attrtype><attwidth Sync="TRUE">1</attwidth><atprecis Sync="TRUE">0</atprecis><attscale Sync="TRUE">0</attscale></attr><attr><attrlabl Sync="TRUE">entzndat</attrlabl><attalias Sync="TRUE">entzndat</attalias><attrtype Sync="TRUE">String</attrtype><attwidth Sync="TRUE">8</attwidth><atprecis Sync="TRUE">0</atprecis><attscale Sync="TRUE">0</attscale></attr><attr><attrlabl Sync="TRUE">entznassm</attrlabl><attalias Sync="TRUE">entznassm</attalias><attrtype Sync="TRUE">Integer</attrtype><attwidth Sync="TRUE">10</attwidth><atprecis Sync="TRUE">10</atprecis><attscale Sync="TRUE">0</attscale></attr><attr><attrlabl Sync="TRUE">plndevdat</attrlabl><attalias Sync="TRUE">plndevdat</attalias><attrtype Sync="TRUE">String</attrtype><attwidth Sync="TRUE">8</attwidth><atprecis Sync="TRUE">0</atprecis><attscale Sync="TRUE">0</attscale></attr><attr><attrlabl Sync="TRUE">nprctstdat</attrlabl><attalias Sync="TRUE">nprctstdat</attalias><attrtype Sync="TRUE">String</attrtype><attwidth Sync="TRUE">8</attwidth><atprecis Sync="TRUE">0</atprecis><attscale Sync="TRUE">0</attscale></attr><attr><attrlabl Sync="TRUE">nprcarea</attrlabl><attalias Sync="TRUE">nprcarea</attalias><attrtype Sync="TRUE">Double</attrtype><attwidth Sync="TRUE">19</attwidth><atprecis Sync="TRUE">18</atprecis><attscale Sync="TRUE">15</attscale></attr><attr><attrlabl Sync="TRUE">nprcluom</attrlabl><attalias Sync="TRUE">nprcluom</attalias><attrtype Sync="TRUE">String</attrtype><attwidth Sync="TRUE">1</attwidth><atprecis Sync="TRUE">0</atprecis><attscale Sync="TRUE">0</attscale></attr><attr><attrlabl Sync="TRUE">homqlcod</attrlabl><attalias Sync="TRUE">homqlcod</attalias><attrtype Sync="TRUE">String</attrtype><attwidth Sync="TRUE">1</attwidth><atprecis Sync="TRUE">0</atprecis><attscale Sync="TRUE">0</attscale></attr><attr><attrlabl Sync="TRUE">homqldat</attrlabl><attalias Sync="TRUE">homqldat</attalias><attrtype Sync="TRUE">String</attrtype><attwidth Sync="TRUE">8</attwidth><atprecis Sync="TRUE">0</atprecis><attscale Sync="TRUE">0</attscale></attr><attr><attrlabl Sync="TRUE">bldg_story</attrlabl><attalias Sync="TRUE">bldg_story</attalias><attrtype Sync="TRUE">String</attrtype><attwidth Sync="TRUE">10</attwidth><atprecis Sync="TRUE">0</atprecis><attscale Sync="TRUE">0</attscale></attr><attr><attrlabl Sync="TRUE">bldg_units</attrlabl><attalias Sync="TRUE">bldg_units</attalias><attrtype Sync="TRUE">Double</attrtype><attwidth Sync="TRUE">19</attwidth><atprecis Sync="TRUE">19</atprecis><attscale Sync="TRUE">0</attscale></attr><attr><attrlabl Sync="TRUE">resident</attrlabl><attalias Sync="TRUE">resident</attalias><attrtype Sync="TRUE">Integer</attrtype><attwidth Sync="TRUE">10</attwidth><atprecis Sync="TRUE">10</atprecis><attscale Sync="TRUE">0</attscale></attr><attr><attrlabl Sync="TRUE">resi2010</attrlabl><attalias Sync="TRUE">resi2010</attalias><attrtype Sync="TRUE">Integer</attrtype><attwidth Sync="TRUE">10</attwidth><atprecis Sync="TRUE">10</atprecis><attscale Sync="TRUE">0</attscale></attr><attr><attrlabl Sync="TRUE">resi2000</attrlabl><attalias Sync="TRUE">resi2000</attalias><attrtype Sync="TRUE">Integer</attrtype><attwidth Sync="TRUE">10</attwidth><atprecis Sync="TRUE">10</atprecis><attscale Sync="TRUE">0</attscale></attr><attr><attrlabl Sync="TRUE">resi1990</attrlabl><attalias Sync="TRUE">resi1990</attalias><attrtype Sync="TRUE">Integer</attrtype><attwidth Sync="TRUE">10</attwidth><atprecis Sync="TRUE">10</atprecis><attscale Sync="TRUE">0</attscale></attr><attr><attrlabl Sync="TRUE">resiuths</attrlabl><attalias Sync="TRUE">resiuths</attalias><attrtype Sync="TRUE">Integer</attrtype><attwidth Sync="TRUE">10</attwidth><atprecis Sync="TRUE">10</atprecis><attscale Sync="TRUE">0</attscale></attr><attr><attrlabl Sync="TRUE">aprtment</attrlabl><attalias Sync="TRUE">aprtment</attalias><attrtype Sync="TRUE">Integer</attrtype><attwidth Sync="TRUE">10</attwidth><atprecis Sync="TRUE">10</atprecis><attscale Sync="TRUE">0</attscale></attr><attr><attrlabl Sync="TRUE">trailer</attrlabl><attalias Sync="TRUE">trailer</attalias><attrtype Sync="TRUE">Integer</attrtype><attwidth Sync="TRUE">10</attwidth><atprecis Sync="TRUE">10</atprecis><attscale Sync="TRUE">0</attscale></attr><attr><attrlabl Sync="TRUE">special</attrlabl><attalias Sync="TRUE">special</attalias><attrtype Sync="TRUE">Integer</attrtype><attwidth Sync="TRUE">10</attwidth><atprecis Sync="TRUE">10</atprecis><attscale Sync="TRUE">0</attscale></attr><attr><attrlabl Sync="TRUE">other</attrlabl><attalias Sync="TRUE">other</attalias><attrtype Sync="TRUE">Integer</attrtype><attwidth Sync="TRUE">10</attwidth><atprecis Sync="TRUE">10</atprecis><attscale Sync="TRUE">0</attscale></attr><attr><attrlabl Sync="TRUE">ptype</attrlabl><attalias Sync="TRUE">ptype</attalias><attrtype Sync="TRUE">Integer</attrtype><attwidth Sync="TRUE">10</attwidth><atprecis Sync="TRUE">10</atprecis><attscale Sync="TRUE">0</attscale></attr><attr><attrlabl Sync="TRUE">sdatwebadr</attrlabl><attalias Sync="TRUE">sdatwebadr</attalias><attrtype Sync="TRUE">String</attrtype><attwidth Sync="TRUE">140</attwidth><atprecis Sync="TRUE">0</atprecis><attscale Sync="TRUE">0</attscale></attr><attr><attrlabl Sync="TRUE">existing</attrlabl><attalias Sync="TRUE">existing</attalias><attrtype Sync="TRUE">String</attrtype><attwidth Sync="TRUE">11</attwidth><atprecis Sync="TRUE">0</atprecis><attscale Sync="TRUE">0</attscale></attr><attr><attrlabl Sync="TRUE">seqnumb</attrlabl><attalias Sync="TRUE">seqnumb</attalias><attrtype Sync="TRUE">Integer</attrtype><attwidth Sync="TRUE">10</attwidth><atprecis Sync="TRUE">10</atprecis><attscale Sync="TRUE">0</attscale></attr><attr><attrlabl Sync="TRUE">salesfacto</attrlabl><attalias Sync="TRUE">salesfacto</attalias><attrtype Sync="TRUE">Double</attrtype><attwidth Sync="TRUE">19</attwidth><atprecis Sync="TRUE">18</atprecis><attscale Sync="TRUE">15</attscale></attr><attr><attrlabl Sync="TRUE">layer</attrlabl><attalias Sync="TRUE">layer</attalias><attrtype Sync="TRUE">String</attrtype><attwidth Sync="TRUE">100</attwidth><atprecis Sync="TRUE">0</atprecis><attscale Sync="TRUE">0</attscale></attr><attr><attrlabl Sync="TRUE">sf_date</attrlabl><attalias Sync="TRUE">sf_date</attalias><attrtype Sync="TRUE">String</attrtype><attwidth Sync="TRUE">8</attwidth><atprecis Sync="TRUE">0</atprecis><attscale Sync="TRUE">0</attscale></attr><attr><attrlabl Sync="TRUE">sf_propval</attrlabl><attalias Sync="TRUE">sf_propval</attalias><attrtype Sync="TRUE">Double</attrtype><attwidth Sync="TRUE">19</attwidth><atprecis Sync="TRUE">18</atprecis><attscale Sync="TRUE">15</attscale></attr><attr><attrlabl Sync="TRUE">value_2010</attrlabl><attalias Sync="TRUE">value_2010</attalias><attrtype Sync="TRUE">Double</attrtype><attwidth Sync="TRUE">19</attwidth><atprecis Sync="TRUE">18</atprecis><attscale Sync="TRUE">15</attscale></attr><attr><attrlabl Sync="TRUE">value_2011</attrlabl><attalias Sync="TRUE">value_2011</attalias><attrtype Sync="TRUE">Double</attrtype><attwidth Sync="TRUE">19</attwidth><atprecis Sync="TRUE">18</atprecis><attscale Sync="TRUE">15</attscale></attr><attr><attrlabl Sync="TRUE">value_2012</attrlabl><attalias Sync="TRUE">value_2012</attalias><attrtype Sync="TRUE">Double</attrtype><attwidth Sync="TRUE">19</attwidth><atprecis Sync="TRUE">18</atprecis><attscale Sync="TRUE">15</attscale></attr><attr><attrlabl Sync="TRUE">value_2013</attrlabl><attalias Sync="TRUE">value_2013</attalias><attrtype Sync="TRUE">Double</attrtype><attwidth Sync="TRUE">19</attwidth><atprecis Sync="TRUE">18</atprecis><attscale Sync="TRUE">15</attscale></attr><attr><attrlabl Sync="TRUE">value_2014</attrlabl><attalias Sync="TRUE">value_2014</attalias><attrtype Sync="TRUE">Double</attrtype><attwidth Sync="TRUE">19</attwidth><atprecis Sync="TRUE">18</atprecis><attscale Sync="TRUE">15</attscale></attr><attr><attrlabl Sync="TRUE">AvgVel</attrlabl><attalias Sync="TRUE">AvgVel</attalias><attrtype Sync="TRUE">Double</attrtype><attwidth Sync="TRUE">19</attwidth><atprecis Sync="TRUE">18</atprecis><attscale Sync="TRUE">15</attscale></attr><attr><attrlabl Sync="TRUE">fid_1</attrlabl><attalias Sync="TRUE">fid_1</attalias><attrtype Sync="TRUE">Integer</attrtype><attwidth Sync="TRUE">10</attwidth><atprecis Sync="TRUE">10</atprecis><attscale Sync="TRUE">0</attscale></attr><attr><attrlabl Sync="TRUE">cntyname</attrlabl><attalias Sync="TRUE">cntyname</attalias><attrtype Sync="TRUE">String</attrtype><attwidth Sync="TRUE">25</attwidth><atprecis Sync="TRUE">0</atprecis><attscale Sync="TRUE">0</attscale></attr><attr><attrlabl Sync="TRUE">county</attrlabl><attalias Sync="TRUE">county</attalias><attrtype Sync="TRUE">String</attrtype><attwidth Sync="TRUE">5</attwidth><atprecis Sync="TRUE">0</atprecis><attscale Sync="TRUE">0</attscale></attr><attr><attrlabl Sync="TRUE">ct2010_2</attrlabl><attalias Sync="TRUE">ct2010_2</attalias><attrtype Sync="TRUE">String</attrtype><attwidth Sync="TRUE">16</attwidth><atprecis Sync="TRUE">0</atprecis><attscale Sync="TRUE">0</attscale></attr><attr><attrlabl Sync="TRUE">hutype</attrlabl><attalias Sync="TRUE">hutype</attalias><attrtype Sync="TRUE">String</attrtype><attwidth Sync="TRUE">10</attwidth><atprecis Sync="TRUE">0</atprecis><attscale Sync="TRUE">0</attscale></attr><attr><attrlabl Sync="TRUE">sales2010</attrlabl><attalias Sync="TRUE">sales2010</attalias><attrtype Sync="TRUE">Integer</attrtype><attwidth Sync="TRUE">10</attwidth><atprecis Sync="TRUE">10</atprecis><attscale Sync="TRUE">0</attscale></attr><attr><attrlabl Sync="TRUE">med_2010</attrlabl><attalias Sync="TRUE">med_2010</attalias><attrtype Sync="TRUE">Integer</attrtype><attwidth Sync="TRUE">10</attwidth><atprecis Sync="TRUE">10</atprecis><attscale Sync="TRUE">0</attscale></attr><attr><attrlabl Sync="TRUE">mean_2010</attrlabl><attalias Sync="TRUE">mean_2010</attalias><attrtype Sync="TRUE">Integer</attrtype><attwidth Sync="TRUE">10</attwidth><atprecis Sync="TRUE">10</atprecis><attscale Sync="TRUE">0</attscale></attr><attr><attrlabl Sync="TRUE">sales2011</attrlabl><attalias Sync="TRUE">sales2011</attalias><attrtype Sync="TRUE">Double</attrtype><attwidth Sync="TRUE">19</attwidth><atprecis Sync="TRUE">19</atprecis><attscale Sync="TRUE">0</attscale></attr><attr><attrlabl Sync="TRUE">med_2011</attrlabl><attalias Sync="TRUE">med_2011</attalias><attrtype Sync="TRUE">Double</attrtype><attwidth Sync="TRUE">19</attwidth><atprecis Sync="TRUE">19</atprecis><attscale Sync="TRUE">0</attscale></attr><attr><attrlabl Sync="TRUE">mean_2011</attrlabl><attalias Sync="TRUE">mean_2011</attalias><attrtype Sync="TRUE">Double</attrtype><attwidth Sync="TRUE">19</attwidth><atprecis Sync="TRUE">19</atprecis><attscale Sync="TRUE">0</attscale></attr><attr><attrlabl Sync="TRUE">sales2012</attrlabl><attalias Sync="TRUE">sales2012</attalias><attrtype Sync="TRUE">Double</attrtype><attwidth Sync="TRUE">19</attwidth><atprecis Sync="TRUE">19</atprecis><attscale Sync="TRUE">0</attscale></attr><attr><attrlabl Sync="TRUE">med_2012</attrlabl><attalias Sync="TRUE">med_2012</attalias><attrtype Sync="TRUE">Double</attrtype><attwidth Sync="TRUE">19</attwidth><atprecis Sync="TRUE">19</atprecis><attscale Sync="TRUE">0</attscale></attr><attr><attrlabl Sync="TRUE">mean_2012</attrlabl><attalias Sync="TRUE">mean_2012</attalias><attrtype Sync="TRUE">Double</attrtype><attwidth Sync="TRUE">19</attwidth><atprecis Sync="TRUE">19</atprecis><attscale Sync="TRUE">0</attscale></attr><attr><attrlabl Sync="TRUE">sales2013</attrlabl><attalias Sync="TRUE">sales2013</attalias><attrtype Sync="TRUE">Double</attrtype><attwidth Sync="TRUE">19</attwidth><atprecis Sync="TRUE">19</atprecis><attscale Sync="TRUE">0</attscale></attr><attr><attrlabl Sync="TRUE">med_2013</attrlabl><attalias Sync="TRUE">med_2013</attalias><attrtype Sync="TRUE">Double</attrtype><attwidth Sync="TRUE">19</attwidth><atprecis Sync="TRUE">19</atprecis><attscale Sync="TRUE">0</attscale></attr><attr><attrlabl Sync="TRUE">mean_2013</attrlabl><attalias Sync="TRUE">mean_2013</attalias><attrtype Sync="TRUE">Double</attrtype><attwidth Sync="TRUE">19</attwidth><atprecis Sync="TRUE">19</atprecis><attscale Sync="TRUE">0</attscale></attr><attr><attrlabl Sync="TRUE">sales2014</attrlabl><attalias Sync="TRUE">sales2014</attalias><attrtype Sync="TRUE">Double</attrtype><attwidth Sync="TRUE">19</attwidth><atprecis Sync="TRUE">19</atprecis><attscale Sync="TRUE">0</attscale></attr><attr><attrlabl Sync="TRUE">med_2014</attrlabl><attalias Sync="TRUE">med_2014</attalias><attrtype Sync="TRUE">Double</attrtype><attwidth Sync="TRUE">19</attwidth><atprecis Sync="TRUE">19</atprecis><attscale Sync="TRUE">0</attscale></attr><attr><attrlabl Sync="TRUE">mean_2014</attrlabl><attalias Sync="TRUE">mean_2014</attalias><attrtype Sync="TRUE">Double</attrtype><attwidth Sync="TRUE">19</attwidth><atprecis Sync="TRUE">19</atprecis><attscale Sync="TRUE">0</attscale></attr><attr><attrlabl Sync="TRUE">OBJECTID_1</attrlabl><attalias Sync="TRUE">OBJECTID_1</attalias><attrtype Sync="TRUE">Integer</attrtype><attwidth Sync="TRUE">10</attwidth><atprecis Sync="TRUE">10</atprecis><attscale Sync="TRUE">0</attscale></attr><attr><attrlabl Sync="TRUE">TAG</attrlabl><attalias Sync="TRUE">TAG</attalias><attrtype Sync="TRUE">String</attrtype><attwidth Sync="TRUE">80</attwidth><atprecis Sync="TRUE">0</atprecis><attscale Sync="TRUE">0</attscale></attr><attr><attrlabl Sync="TRUE">S_TYPE</attrlabl><attalias Sync="TRUE">S_TYPE</attalias><attrtype Sync="TRUE">String</attrtype><attwidth Sync="TRUE">254</attwidth><atprecis Sync="TRUE">0</atprecis><attscale Sync="TRUE">0</attscale></attr><attr><attrlabl Sync="TRUE">TAG_NAME</attrlabl><attalias Sync="TRUE">TAG_NAME</attalias><attrtype Sync="TRUE">String</attrtype><attwidth Sync="TRUE">254</attwidth><atprecis Sync="TRUE">0</atprecis><attscale Sync="TRUE">0</attscale></attr><attr><attrlabl Sync="TRUE">FScore</attrlabl><attalias Sync="TRUE">FScore</attalias><attrtype Sync="TRUE">Double</attrtype><attwidth Sync="TRUE">19</attwidth><atprecis Sync="TRUE">18</atprecis><attscale Sync="TRUE">11</attscale></attr></detailed></eainfo><mdDateSt Sync="TRUE">20190929</mdDateSt></metadata>
